cleepcli/__init__.py
cleepcli/check.py
cleepcli/ci.py
cleepcli/cleepapi.py
cleepcli/config.py
cleepcli/console.py
cleepcli/docs.py
cleepcli/file.py
cleepcli/git.py
cleepcli/module.py
cleepcli/package.py
cleepcli/test.py
cleepcli/tools.py
cleepcli/version.py
cleepcli/watch.py
cleepcli-1.43.4.data/scripts/ccli
cleepcli-1.43.4.data/scripts/cleep-cli
cleepcli-1.43.4.dist-info/LICENSE
cleepcli-1.43.4.dist-info/METADATA
cleepcli-1.43.4.dist-info/WHEEL
cleepcli-1.43.4.dist-info/top_level.txt
cleepcli-1.43.4.dist-info/RECORD
