Metadata-Version: 2.1
Name: cleepcli
Version: 1.43.4
Summary: Cleep-cli helps developers to build great Cleep applications from command line.
Home-page: https://github.com/CleepDevice/cleep-cli
Author: Tanguy Bonneau
Author-email: tanguy.bonneau@gmail.com
Maintainer: Tanguy Bonneau
Maintainer-email: tanguy.bonneau@gmail.com
License: UNKNOWN
Platform: UNKNOWN
License-File: LICENSE
Requires-Dist: Click (<9.0,>=8.0)
Requires-Dist: watchdog (<4.0.0,>=3.0.0)
Requires-Dist: Sphinx (<6.0.0,>=5.0.0)
Requires-Dist: sphinx-rtd-theme (>=1.0.0)
Requires-Dist: CProfileV (>=1.0.7)
Requires-Dist: PyGithub (==1.54.1)
Requires-Dist: pylint (<3.0.0,>=2.11.1)
Requires-Dist: semver (==3.0.0)
Requires-Dist: coverage (==7.2.7)
Requires-Dist: passlib (==1.7.4)
Requires-Dist: requests (==2.31.0)
Requires-Dist: psutil (==5.9.4)
